README.md
setup.py
totp_cli.egg-info/PKG-INFO
totp_cli.egg-info/SOURCES.txt
totp_cli.egg-info/dependency_links.txt
totp_cli.egg-info/entry_points.txt
totp_cli.egg-info/requires.txt
totp_cli.egg-info/top_level.txt
totpauth/__init__.py
totpauth/totp.py
totpauth/database/info.json